conversiontools/__init__.py
conversiontools/client.py
conversiontools/py.typed
conversiontools/api/__init__.py
conversiontools/api/config.py
conversiontools/api/files.py
conversiontools/api/http.py
conversiontools/api/tasks.py
conversiontools/models/__init__.py
conversiontools/models/task.py
conversiontools/types/__init__.py
conversiontools/types/config.py
conversiontools/utils/__init__.py
conversiontools/utils/errors.py
conversiontools/utils/polling.py
conversiontools/utils/progress.py
conversiontools/utils/retry.py
conversiontools/utils/validation.py
conversiontools-2.0.0.dist-info/licenses/LICENSE
conversiontools-2.0.0.dist-info/METADATA
conversiontools-2.0.0.dist-info/WHEEL
conversiontools-2.0.0.dist-info/top_level.txt
conversiontools-2.0.0.dist-info/RECORD
