Metadata-Version: 2.4
Name: conversiontools
Version: 2.0.0
Summary: Modern Python library to convert files using Conversion Tools API at https://conversiontools.io - supports both sync and async with full type hints
Author-email: Conversion Tools <info@conversiontools.io>
Maintainer-email: Conversion Tools <info@conversiontools.io>
License-Expression: MIT
Project-URL: Homepage, https://github.com/conversiontools/conversiontools-python
Project-URL: Documentation, https://conversiontools.io/api-documentation
Project-URL: Repository, https://github.com/conversiontools/conversiontools-python
Project-URL: Bug Tracker, https://github.com/conversiontools/conversiontools-python/issues
Keywords: conversiontools,conversion,tools,convert,document,file,api,sdk,client,xml,json,excel,pdf,csv,async,httpx
Classifier: Development Status :: 5 - Production/Stable
Classifier: Intended Audience :: Developers
Classifier: Operating System :: OS Independent
Classifier: Programming Language :: Python :: 3
Classifier: Programming Language :: Python :: 3.8
Classifier: Programming Language :: Python :: 3.9
Classifier: Programming Language :: Python :: 3.10
Classifier: Programming Language :: Python :: 3.11
Classifier: Programming Language :: Python :: 3.12
Classifier: Topic :: Software Development :: Libraries
Classifier: Topic :: Software Development :: Libraries :: Python Modules
Classifier: Typing :: Typed
Requires-Python: >=3.8
License-File: LICENSE
Requires-Dist: httpx>=0.24.0
Requires-Dist: typing-extensions>=4.0.0
Provides-Extra: dev
Requires-Dist: pytest>=7.0.0; extra == "dev"
Requires-Dist: pytest-asyncio>=0.21.0; extra == "dev"
Requires-Dist: black>=24.3.0; extra == "dev"
Requires-Dist: mypy>=1.0.0; extra == "dev"
Requires-Dist: ruff>=0.1.0; extra == "dev"
Dynamic: license-file
